Metadata-Version: 2.1
Name: CloudsOfArx
Version: 0.4.0
Summary: Web Scraper package for generating wordclouds from research paper abstracts.
Home-page: https://github.com/James11222/CloudsOfArx/
Author: James Sunseri
Author-email: jamessunseri@berkeley.edu
License: MIT
Project-URL: Bug Reports, https://github.com/James11222/CloudsOfArx/issues
Project-URL: Funding, https://donate.pypi.org
Project-URL: Check out my Website!, http://www.jamessunseri.com
Project-URL: Source, https://github.com/James11222/CloudsOfArx/
Keywords: ArXiv,ADS,wordcloud
Platform: any
Classifier: Development Status :: 4 - Beta
Classifier: Intended Audience :: Developers
Classifier: Topic :: Software Development :: Build Tools
Classifier: License :: OSI Approved :: MIT License
Classifier: Programming Language :: Python :: 3
Classifier: Programming Language :: Python :: 3.6
Classifier: Programming Language :: Python :: 3.7
Classifier: Programming Language :: Python :: 3.8
Classifier: Programming Language :: Python :: 3.9
Classifier: Programming Language :: Python :: 3.10
Classifier: Programming Language :: Python :: 3 :: Only
Requires-Python: >=3.6, <4
License-File: LICENSE
